# 字符串拼接+和+=的执行过程

Java语言其实是支持运算符重载的，不过只有+和+=，而且是专门为String类设计的。

**运算符重载就是： 使得两个对象相加的行为符合你的需求。**

~~~java
String str1 = "he";
String str2 = "llo";
String str3 = "world";
String str4 = str1 + str2 + str3;
~~~

这串代码对应的字节码是

~~~c
0: ldc           #2                  // String he
2: astore_1
3: ldc           #3                  // String llo
5: astore_2
6: ldc           #4                  // String world
8: astore_3
9: new           #5                  // class StringBuilder
12: dup
13: invokespecial #6                  // Method StringBuilder."<init>":()V
16: aload_1
17: invokevirtual #7                  // Method StringBuilder.append:(Ljava/lang/String;)Ljava/lang/StringBuilder;
20: aload_2
21: invokevirtual #7                  // Method StringBuilder.append:(Ljava/lang/String;)Ljava/lang/StringBuilder;
24: aload_3
25: invokevirtual #7                  // Method StringBuilder.append:(Ljava/lang/String;)Ljava/lang/StringBuilder;
28: invokevirtual #8                  // Method StringBuilder.toString:()Ljava/lang/String;
31: astore        4
~~~

我们会发现，我们首先创建了一个StringBuilder方法， 然后通过Stringbuilder方法的apped方法进行相加，然后在调用toString方法进行生成字符串。

~~~java
String[] arr = {"he", "llo", "world"};
String str = "";
for (int i = 0; i < arr.length; i++) {
    str += arr[i];
}
System.out.println(str);
~~~

如果是在循环内，那么每个循环都会创建一个StringBuilder对象，这也是缺点之一，不过在JDK1.9得到了解决了。

## 和常量进行+ 或者+= 

~~~java
final String str1 = "str";
final String str2 = "ing";
// 下面两个表达式其实是等价的
String c = "str" + "ing";// 常量池中的对象
String d = str1 + str2; // 常量池中的对象
System.out.println(c == d);// true

代码2
String str1 = "str";
final String str2 = "ing";
// 下面两个表达式其实是等价的
String c = "str" + "ing";// 常量池中的对象
String d = str1 + str2; // 常量池中的对象
System.out.println(c == d);// true
~~~

如果是这个代码。那么就会优化为c= string,d=string。因为译器在程序编译期就可以确定它的值，其效果就相当于访问常量，就会把结果放到字符串常量池，如果不能确认那么就和上面的一样处理。

```java
static final String s1 ="1";
public static void main(String[] args) {
    String s = new Scanner(System.in).next();
    System.out.println(s1+s);
}
```

